{
	"info": {
		"_postman_id": "1688f940-6e02-4c46-af40-037839c13703",
		"name": "New Collection",
		"schema": "https://schema.getpostman.com/json/collection/v2.1.0/collection.json",
		"_exporter_id": "26290912",
		"_collection_link": "https://orange-comet-29342.postman.co/workspace/disney~3080bfa6-ccc9-4e52-a966-82e51552f895/collection/26290912-1688f940-6e02-4c46-af40-037839c13703?action=share&creator=26290912&source=collection_link"
	},
	"item": [
		{
			"name": "coleccion personajes",
			"item": [
				{
					"name": "get personajes by Id detalle",
					"request": {
						"method": "GET",
						"header": [],
						"url": {
							"raw": "http://localhost:5000/characters/getById/1",
							"protocol": "http",
							"host": [
								"localhost"
							],
							"port": "5000",
							"path": [
								"characters",
								"getById",
								"1"
							]
						}
					},
					"response": []
				},
				{
					"name": "Actualizar personaje by Id",
					"request": {
						"method": "PUT",
						"header": [],
						"body": {
							"mode": "raw",
							"raw": "",
							"options": {
								"raw": {
									"language": "json"
								}
							}
						},
						"url": {
							"raw": "http://localhost:5000/characters/8",
							"protocol": "http",
							"host": [
								"localhost"
							],
							"port": "5000",
							"path": [
								"characters",
								"8"
							]
						}
					},
					"response": []
				},
				{
					"name": "Crear personaje",
					"request": {
						"method": "POST",
						"header": [],
						"body": {
							"mode": "raw",
							"raw": "{\r\n    \"imagen\" :\"wawa\",\r\n    \"nombre\" : \"federico fod\",\r\n    \"edad\" : 44 ,\r\n    \"peso\" : 442,\r\n    \"historia\": \"palala\"\r\n}",
							"options": {
								"raw": {
									"language": "json"
								}
							}
						},
						"url": {
							"raw": "http://localhost:5000/characters",
							"protocol": "http",
							"host": [
								"localhost"
							],
							"port": "5000",
							"path": [
								"characters"
							]
						}
					},
					"response": []
				},
				{
					"name": "Borrar personaje by Id",
					"request": {
						"method": "DELETE",
						"header": [],
						"body": {
							"mode": "raw",
							"raw": "{\r\n\"imagen\" : \"a\" ,\r\n\"nombre\" : \"ricardo tapia\",\r\n\"edad\" : 2 ,\r\n\"peso\" : 32,\r\n\"historia\" : \"hola\"\r\n\r\n\r\n}",
							"options": {
								"raw": {
									"language": "json"
								}
							}
						},
						"url": {
							"raw": "http://localhost:5000/characters/5",
							"protocol": "http",
							"host": [
								"localhost"
							],
							"port": "5000",
							"path": [
								"characters",
								"5"
							]
						}
					},
					"response": []
				},
				{
					"name": "get personajes",
					"request": {
						"method": "GET",
						"header": [],
						"url": {
							"raw": "http://localhost:5000/characters?nombre=Naomi Lapaglia",
							"protocol": "http",
							"host": [
								"localhost"
							],
							"port": "5000",
							"path": [
								"characters"
							],
							"query": [
								{
									"key": "nombre",
									"value": "Naomi Lapaglia"
								}
							]
						}
					},
					"response": []
				}
			]
		},
		{
			"name": "coleccion peliculas",
			"item": [
				{
					"name": "get peli by id detalle",
					"request": {
						"method": "GET",
						"header": [],
						"url": {
							"raw": "http://localhost:5000/movies/1",
							"protocol": "http",
							"host": [
								"localhost"
							],
							"port": "5000",
							"path": [
								"movies",
								"1"
							]
						}
					},
					"response": []
				},
				{
					"name": "Actualizar pelicula",
					"request": {
						"method": "PUT",
						"header": [],
						"body": {
							"mode": "raw",
							"raw": "  {\r\n      \"imagen\": \"nao nao\",\r\n    \"titulo\": \"rio mistico\",\r\n    \"calificacion\": 3,\r\n    \"fechaCreacion\": \"04/09/2006\"\r\n  }",
							"options": {
								"raw": {
									"language": "json"
								}
							}
						},
						"url": {
							"raw": "http://localhost:5000/movies/2",
							"protocol": "http",
							"host": [
								"localhost"
							],
							"port": "5000",
							"path": [
								"movies",
								"2"
							]
						}
					},
					"response": []
				},
				{
					"name": "Crear pelicula",
					"request": {
						"method": "POST",
						"header": [],
						"body": {
							"mode": "raw",
							"raw": "{\r\n    \"imagen\": \"nao nao\",\r\n    \"titulo\": \"wodolian\",\r\n    \"calificacion\": 3,\r\n    \"fechaCreacion\": \"04/09/2006\"\r\n}",
							"options": {
								"raw": {
									"language": "json"
								}
							}
						},
						"url": {
							"raw": "http://localhost:5000/movies",
							"protocol": "http",
							"host": [
								"localhost"
							],
							"port": "5000",
							"path": [
								"movies"
							]
						}
					},
					"response": []
				},
				{
					"name": "Borrar pelicula",
					"request": {
						"method": "DELETE",
						"header": [],
						"url": {
							"raw": "http://localhost:5000/movies/3",
							"protocol": "http",
							"host": [
								"localhost"
							],
							"port": "5000",
							"path": [
								"movies",
								"3"
							]
						}
					},
					"response": []
				},
				{
					"name": "get peliculas",
					"request": {
						"method": "GET",
						"header": [],
						"url": {
							"raw": "http://localhost:5000/movies/?orden=DESC&nombre=Rio%20mistico",
							"protocol": "http",
							"host": [
								"localhost"
							],
							"port": "5000",
							"path": [
								"movies",
								""
							],
							"query": [
								{
									"key": "orden",
									"value": "DESC"
								},
								{
									"key": "nombre",
									"value": "Rio%20mistico"
								}
							]
						}
					},
					"response": []
				}
			]
		},
		{
			"name": "authentication",
			"item": [
				{
					"name": "http://localhost:5000/auth/login",
					"request": {
						"method": "GET",
						"header": [],
						"url": {
							"raw": "http://localhost:5000/auth/login",
							"protocol": "http",
							"host": [
								"localhost"
							],
							"port": "5000",
							"path": [
								"auth",
								"login"
							]
						}
					},
					"response": []
				}
			]
		}
	]
}